quote/__init__.py
quote/main.py
quote/quote.py
quote/quotes.txt
quote/sorry.txt
quote4py-1.1.2.dist-info/METADATA
quote4py-1.1.2.dist-info/WHEEL
quote4py-1.1.2.dist-info/top_level.txt
quote4py-1.1.2.dist-info/RECORD
