Metadata-Version: 2.1
Name: quote4py
Version: 1.1.2
Summary: best yaoyao
Author: netcat
Author-email: 974123274@qq.com
